bin/__init__.py
pywolf/__init__.py
pywolf/application/__init__.py
pywolf/application/application.py
pywolf/application/bootstrap.py
pywolf/application/config.py
pywolf/application/context.py
pywolf/application/path.py
pywolf/cli/__init__.py
pywolf/cli/command.py
pywolf/db/__init__.py
pywolf/db/config.py
pywolf/db/db.py
pywolf/db/db_config_demo.yaml
pywolf/db/executor.py
pywolf/db/result.py
pywolf/db/sqlutils.py
pywolf/exception/base.py
pywolf/exception/business.py
pywolf/exception/system.py
pywolf/middleware/__init__.py
pywolf/middleware/cache/__init__.py
pywolf/middleware/cache/cache.py
pywolf/middleware/cache/cache_config_demo.yaml
pywolf/middleware/cache/config.py
pywolf/net/__init__.py
pywolf/net/connection.py
pywolf/net/httpclient.py
pywolf/net/urlparser.py
pywolf/utils/__init__.py
pywolf/utils/fileutils.py
pywolf/utils/pathutils.py
pywolf/utils/strutils.py
pywolf/utils/typeutils.py
pywolf/utils/urlutils.py
pywolf-0.3.5.dist-info/LICENSE
pywolf-0.3.5.dist-info/METADATA
pywolf-0.3.5.dist-info/WHEEL
pywolf-0.3.5.dist-info/RECORD
